uqo/Problem.py
uqo/Response.py
uqo/UQOExceptions.py
uqo/__init__.py
uqo/generate_certificates.py
uqo/client/__init__.py
uqo/client/config.py
uqo/client/connection.py
uqo/client/uqo_public.key
uqo/examples/__init__.py
uqo/examples/examples.py
uqo/examples/graph_coloring_example.py
uqo/examples/util.py
uqo-0.0.2.6.dist-info/LICENSE
uqo-0.0.2.6.dist-info/METADATA
uqo-0.0.2.6.dist-info/WHEEL
uqo-0.0.2.6.dist-info/top_level.txt
uqo-0.0.2.6.dist-info/RECORD
