Metadata-Version: 2.1
Name: uqo
Version: 0.0.2.6
Summary: Client of the optimization framework UQO
Author-email: QAR-Lab Munich <Sebastian.Zielinski@ifi.lmu.de>
Project-URL: Homepage, https://github.com/QAR-Lab/uqoclient
Classifier: Programming Language :: Python :: 3
Classifier: License :: OSI Approved :: MIT License
Classifier: Operating System :: OS Independent
Requires-Python: >=3.7
License-File: LICENSE
Requires-Dist: dimod ==0.10.16
Requires-Dist: dwave-networkx ==0.8.8
Requires-Dist: prettytable ==2.0.0
Requires-Dist: pyzmq ==22.0.2
Requires-Dist: matplotlib ==3.3.2
